.gitignore
LICENSE.txt
README.md
pyproject.toml
requirements.txt
bbg_fetch/__init__.py
bbg_fetch/bbg_fetch.py
bbg_fetch.egg-info/PKG-INFO
bbg_fetch.egg-info/SOURCES.txt
bbg_fetch.egg-info/dependency_links.txt
bbg_fetch.egg-info/requires.txt
bbg_fetch.egg-info/top_level.txt