Metadata-Version: 2.4
Name: bbg-fetch
Version: 1.1.1
Summary: Python functionality for getting different data from Bloomberg: prices, implied vols, fundamentals
Author-email: Artur Sepp <artursepp@gmail.com>
Maintainer-email: Artur Sepp <artursepp@gmail.com>
License: GNU GENERAL PUBLIC LICENSE
Project-URL: Homepage, https://github.com/ArturSepp/BloombergFetch
Project-URL: Documentation, https://github.com/ArturSepp/BloombergFetch/blob/main/README.md
Project-URL: Repository, https://github.com/ArturSepp/BloombergFetch.git
Project-URL: Issues, https://github.com/ArturSepp/BloombergFetch/issues
Project-URL: Changelog, https://github.com/ArturSepp/BloombergFetch/blob/main/CHANGELOG.md
Keywords: bloomberg,bloomberg api,bloomberg terminal,financial data,market data,equities,futures,options,bonds,fx data,implied volatility,fundamentals,credit data,quantitative finance,data fetching,xbbg,blpapi
Classifier: Development Status :: 4 - Beta
Classifier: Intended Audience :: Developers
Classifier: Intended Audience :: Financial and Insurance Industry
Classifier: Intended Audience :: Science/Research
Classifier: License :: OSI Approved :: GNU General Public License v3 or later (GPLv3+)
Classifier: Operating System :: OS Independent
Classifier: Programming Language :: Python
Classifier: Programming Language :: Python :: 3
Classifier: Programming Language :: Python :: 3.8
Classifier: Programming Language :: Python :: 3.9
Classifier: Programming Language :: Python :: 3.10
Classifier: Programming Language :: Python :: 3.11
Classifier: Programming Language :: Python :: 3.12
Classifier: Programming Language :: Python :: 3.13
Classifier: Topic :: Office/Business :: Financial :: Investment
Classifier: Topic :: Scientific/Engineering :: Mathematics
Classifier: Topic :: Scientific/Engineering :: Information Analysis
Classifier: Topic :: Software Development :: Libraries :: Python Modules
Requires-Python: >=3.8
License-File: LICENSE.txt
Requires-Dist: numpy>=2.2.6
Requires-Dist: pandas>=2.3.1
Requires-Dist: pyarrow>=18.0.0
Requires-Dist: xbbg>=0.7.8
Provides-Extra: jupyter
Requires-Dist: jupyter>=1.0.0; extra == "jupyter"
Requires-Dist: notebook>=6.5.0; extra == "jupyter"
Requires-Dist: jupyterlab>=3.0.0; extra == "jupyter"
Requires-Dist: ipykernel>=6.0.0; extra == "jupyter"
Requires-Dist: ipywidgets>=8.0.0; extra == "jupyter"
Provides-Extra: dev
Requires-Dist: pytest>=7.0.0; extra == "dev"
Requires-Dist: pytest-cov>=4.0.0; extra == "dev"
Requires-Dist: pytest-mock>=3.10.0; extra == "dev"
Requires-Dist: pytest-xdist>=3.0.0; extra == "dev"
Requires-Dist: black>=22.0.0; extra == "dev"
Requires-Dist: flake8>=5.0.0; extra == "dev"
Requires-Dist: mypy>=1.0.0; extra == "dev"
Requires-Dist: isort>=5.10.0; extra == "dev"
Requires-Dist: pre-commit>=3.0.0; extra == "dev"
Provides-Extra: all
Requires-Dist: bbg-fetch[dev,jupyter]; extra == "all"
Provides-Extra: extras
Requires-Dist: bbg-fetch[jupyter,reports]; extra == "extras"
Dynamic: license-file
